proxql/__init__.py
proxql/exceptions.py
proxql/parser.py
proxql/policy.py
proxql/py.typed
proxql/result.py
proxql/validator.py
proxql-0.1.0.dist-info/METADATA
proxql-0.1.0.dist-info/WHEEL
proxql-0.1.0.dist-info/licenses/LICENSE
proxql-0.1.0.dist-info/RECORD
