Metadata-Version: 2.4
Name: proxql
Version: 0.1.0
Summary: SQL validation library that blocks destructive queries from LLM-generated SQL
Project-URL: Homepage, https://github.com/zeredbaron/proxql
Project-URL: Repository, https://github.com/zeredbaron/proxql
Project-URL: Issues, https://github.com/zeredbaron/proxql/issues
Author: Baron
License-Expression: Apache-2.0
License-File: LICENSE
Keywords: ai,database,llm,security,sql,validation
Classifier: Development Status :: 3 - Alpha
Classifier: Intended Audience :: Developers
Classifier: License :: OSI Approved :: Apache Software License
Classifier: Programming Language :: Python :: 3
Classifier: Programming Language :: Python :: 3.10
Classifier: Programming Language :: Python :: 3.11
Classifier: Programming Language :: Python :: 3.12
Classifier: Programming Language :: Python :: 3.13
Classifier: Topic :: Database
Classifier: Topic :: Security
Classifier: Typing :: Typed
Requires-Python: >=3.10
Requires-Dist: sqlglot>=26.0.0
Provides-Extra: dev
Requires-Dist: mypy>=1.13; extra == 'dev'
Requires-Dist: pytest-cov>=4.0; extra == 'dev'
Requires-Dist: pytest>=8.0; extra == 'dev'
Requires-Dist: ruff>=0.8; extra == 'dev'
